[{"t":91509,"p":5530,"v":20,"bs":4},{"t":92421,"p":5520,"v":215,"bs":4},{"t":92457,"p":5530,"v":358,"bs":4},{"t":92500,"p":5530,"v":358,"bs":2},{"t":93000,"p":5520,"v":336,"bs":1},{"t":93003,"p":5560,"v":412,"bs":2},{"t":93006,"p":5570,"v":101,"bs":2},{"t":93012,"p":5570,"v":2,"bs":1},{"t":93018,"p":5540,"v":12,"bs":1},{"t":93033,"p":5540,"v":101,"bs":1},{"t":93036,"p":5550,"v":100,"bs":2},{"t":93039,"p":5540,"v":41,"bs":1},{"t":93045,"p":5550,"v":26,"bs":1},{"t":93048,"p":5560,"v":31,"bs":2},{"t":93051,"p":5550,"v":3,"bs":1},{"t":93057,"p":5560,"v":11,"bs":2},{"t":93103,"p":5550,"v":55,"bs":1},{"t":93109,"p":5560,"v":40,"bs":2},{"t":93112,"p":5550,"v":27,"bs":1},{"t":93115,"p":5560,"v":29,"bs":2},{"t":93118,"p":5560,"v":320,"bs":2},{"t":93121,"p":5560,"v":82,"bs":1},{"t":93124,"p":5560,"v":20,"bs":1},{"t":93139,"p":5560,"v":26,"bs":1},{"t":93145,"p":5570,"v":9,"bs":2},{"t":93148,"p":5560,"v":20,"bs":1},{"t":93157,"p":5560,"v":123,"bs":1},{"t":93209,"p":5550,"v":113,"bs":1},{"t":93212,"p":5550,"v":20,"bs":1},{"t":93215,"p":5550,"v":76,"bs":1},{"t":93221,"p":5550,"v":180,"bs":2},{"t":93224,"p":5540,"v":14,"bs":1},{"t":93233,"p":5550,"v":14,"bs":2},{"t":93236,"p":5540,"v":50,"bs":1},{"t":93239,"p":5550,"v":69,"bs":2},{"t":93242,"p":5550,"v":85,"bs":2},{"t":93245,"p":5550,"v":6,"bs":1},{"t":93300,"p":5560,"v":50,"bs":2},{"t":93306,"p":5560,"v":8,"bs":2},{"t":93309,"p":5550,"v":32,"bs":1},{"t":93315,"p":5570,"v":135,"bs":2},{"t":93321,"p":5560,"v":47,"bs":1},{"t":93324,"p":5560,"v":24,"bs":1},{"t":93342,"p":5560,"v":14,"bs":1},{"t":93348,"p":5550,"v":91,"bs":1},{"t":93354,"p":5560,"v":4,"bs":2},{"t":93357,"p":5550,"v":63,"bs":1},{"t":93400,"p":5550,"v":48,"bs":1},{"t":93409,"p":5550,"v":114,"bs":1},{"t":93412,"p":5550,"v":100,"bs":1},{"t":93421,"p":5560,"v":93,"bs":2},{"t":93424,"p":5560,"v":10,"bs":1},{"t":93433,"p":5570,"v":6,"bs":2},{"t":93436,"p":5560,"v":17,"bs":1},{"t":93442,"p":5560,"v":135,"bs":1},{"t":93445,"p":5570,"v":446,"bs":2},{"t":93457,"p":5570,"v":100,"bs":1},{"t":93503,"p":5600,"v":108,"bs":2},{"t":93512,"p":5600,"v":2,"bs":2},{"t":93524,"p":5570,"v":15,"bs":1},{"t":93530,"p":5600,"v":10,"bs":2},{"t":93533,"p":5600,"v":153,"bs":2},{"t":93536,"p":5600,"v":28,"bs":1},{"t":93542,"p":5610,"v":239,"bs":2},{"t":93548,"p":5610,"v":3,"bs":1},{"t":93551,"p":5610,"v":6,"bs":1},{"t":93557,"p":5610,"v":29,"bs":2},{"t":93600,"p":5610,"v":20,"bs":1},{"t":93603,"p":5610,"v":39,"bs":1},{"t":93606,"p":5610,"v":25,"bs":2},{"t":93609,"p":5610,"v":9,"bs":2},{"t":93615,"p":5600,"v":108,"bs":1},{"t":93618,"p":5600,"v":13,"bs":1},{"t":93621,"p":5600,"v":60,"bs":1},{"t":93624,"p":5600,"v":52,"bs":1},{"t":93627,"p":5570,"v":20,"bs":1},{"t":93630,"p":5600,"v":2,"bs":2},{"t":93642,"p":5580,"v":20,"bs":1},{"t":93648,"p":5590,"v":158,"bs":2},{"t":93651,"p":5590,"v":10,"bs":1},{"t":93712,"p":5590,"v":109,"bs":1},{"t":93727,"p":5590,"v":8,"bs":2},{"t":93733,"p":5590,"v":14,"bs":2},{"t":93742,"p":5590,"v":20,"bs":2},{"t":93745,"p":5590,"v":5,"bs":2},{"t":93751,"p":5590,"v":2,"bs":2},{"t":93754,"p":5590,"v":2,"bs":2},{"t":93800,"p":5590,"v":2,"bs":2},{"t":93809,"p":5580,"v":20,"bs":1},{"t":93812,"p":5580,"v":50,"bs":1},{"t":93815,"p":5580,"v":139,"bs":1},{"t":93821,"p":5580,"v":120,"bs":1},{"t":93824,"p":5580,"v":32,"bs":1},{"t":93836,"p":5570,"v":20,"bs":1},{"t":93842,"p":5570,"v":158,"bs":1},{"t":93854,"p":5560,"v":10,"bs":1},{"t":93900,"p":5560,"v":90,"bs":1},{"t":93903,"p":5560,"v":5,"bs":2},{"t":93906,"p":5560,"v":43,"bs":2},{"t":93912,"p":5560,"v":111,"bs":1},{"t":93915,"p":5560,"v":37,"bs":2},{"t":93918,"p":5570,"v":91,"bs":2},{"t":93921,"p":5550,"v":5,"bs":1},{"t":94012,"p":5560,"v":5,"bs":1},{"t":94015,"p":5560,"v":66,"bs":1},{"t":94042,"p":5560,"v":10,"bs":2},{"t":94051,"p":5560,"v":15,"bs":2},{"t":94057,"p":5560,"v":3,"bs":2},{"t":94106,"p":5550,"v":10,"bs":1},{"t":94109,"p":5560,"v":50,"bs":2},{"t":94115,"p":5550,"v":15,"bs":1},{"t":94118,"p":5550,"v":25,"bs":1},{"t":94121,"p":5550,"v":498,"bs":1},{"t":94130,"p":5560,"v":33,"bs":2},{"t":94136,"p":5560,"v":17,"bs":1},{"t":94154,"p":5550,"v":100,"bs":1},{"t":94203,"p":5550,"v":2,"bs":1},{"t":94206,"p":5550,"v":18,"bs":1},{"t":94209,"p":5550,"v":5,"bs":2},{"t":94218,"p":5550,"v":32,"bs":2},{"t":94221,"p":5550,"v":8,"bs":2},{"t":94224,"p":5540,"v":36,"bs":1},{"t":94233,"p":5540,"v":20,"bs":1},{"t":94245,"p":5540,"v":1,"bs":1},{"t":94248,"p":5540,"v":20,"bs":1},{"t":94251,"p":5540,"v":138,"bs":1},{"t":94309,"p":5540,"v":5,"bs":1},{"t":94330,"p":5540,"v":2,"bs":2},{"t":94333,"p":5540,"v":60,"bs":2},{"t":94351,"p":5560,"v":200,"bs":2},{"t":94400,"p":5550,"v":2,"bs":1},{"t":94403,"p":5540,"v":100,"bs":1},{"t":94415,"p":5530,"v":376,"bs":1},{"t":94430,"p":5530,"v":1,"bs":1},{"t":94515,"p":5530,"v":51,"bs":1},{"t":94530,"p":5520,"v":102,"bs":1},{"t":94536,"p":5560,"v":20,"bs":2},{"t":94545,"p":5510,"v":114,"bs":1},{"t":94606,"p":5530,"v":37,"bs":1},{"t":94615,"p":5530,"v":119,"bs":2},{"t":94627,"p":5510,"v":20,"bs":1},{"t":94700,"p":5530,"v":72,"bs":2},{"t":94703,"p":5530,"v":37,"bs":1},{"t":94712,"p":5520,"v":231,"bs":1},{"t":94724,"p":5520,"v":8,"bs":1},{"t":94736,"p":5530,"v":8,"bs":1},{"t":94748,"p":5530,"v":21,"bs":2},{"t":94757,"p":5530,"v":12,"bs":1},{"t":94818,"p":5520,"v":234,"bs":1},{"t":94827,"p":5540,"v":21,"bs":2},{"t":94833,"p":5510,"v":231,"bs":1},{"t":94839,"p":5530,"v":14,"bs":1},{"t":94842,"p":5530,"v":51,"bs":1},{"t":94857,"p":5500,"v":1342,"bs":1},{"t":94900,"p":5500,"v":78,"bs":2},{"t":94909,"p":5520,"v":98,"bs":1},{"t":94915,"p":5510,"v":10,"bs":2},{"t":94918,"p":5490,"v":70,"bs":1},{"t":94939,"p":5500,"v":33,"bs":1},{"t":94954,"p":5490,"v":324,"bs":1},{"t":94957,"p":5490,"v":50,"bs":2},{"t":95003,"p":5480,"v":226,"bs":1},{"t":95006,"p":5480,"v":9,"bs":2},{"t":95009,"p":5490,"v":38,"bs":2},{"t":95015,"p":5490,"v":323,"bs":2},{"t":95018,"p":5480,"v":14,"bs":1},{"t":95021,"p":5480,"v":10,"bs":2},{"t":95024,"p":5470,"v":45,"bs":1},{"t":95027,"p":5490,"v":411,"bs":2},{"t":95045,"p":5520,"v":1,"bs":2},{"t":95051,"p":5490,"v":41,"bs":1},{"t":95054,"p":5490,"v":5,"bs":2},{"t":95100,"p":5490,"v":11,"bs":2},{"t":95103,"p":5490,"v":13,"bs":2},{"t":95106,"p":5490,"v":50,"bs":2},{"t":95109,"p":5490,"v":80,"bs":2},{"t":95112,"p":5490,"v":10,"bs":2},{"t":95124,"p":5490,"v":15,"bs":1},{"t":95148,"p":5500,"v":103,"bs":1},{"t":95154,"p":5500,"v":10,"bs":2},{"t":95157,"p":5500,"v":8,"bs":2},{"t":95200,"p":5500,"v":5,"bs":2},{"t":95203,"p":5500,"v":4,"bs":2},{"t":95215,"p":5500,"v":50,"bs":2},{"t":95221,"p":5500,"v":22,"bs":2},{"t":95239,"p":5510,"v":1,"bs":2},{"t":95245,"p":5510,"v":122,"bs":2},{"t":95257,"p":5510,"v":32,"bs":1},{"t":95303,"p":5510,"v":20,"bs":1},{"t":95312,"p":5520,"v":37,"bs":2},{"t":95318,"p":5510,"v":112,"bs":1},{"t":95321,"p":5520,"v":217,"bs":2},{"t":95330,"p":5530,"v":169,"bs":2},{"t":95333,"p":5530,"v":240,"bs":1},{"t":95342,"p":5530,"v":105,"bs":1},{"t":95345,"p":5530,"v":105,"bs":1},{"t":95348,"p":5530,"v":126,"bs":2},{"t":95354,"p":5540,"v":210,"bs":2},{"t":95400,"p":5540,"v":10,"bs":2},{"t":95412,"p":5530,"v":200,"bs":1},{"t":95415,"p":5530,"v":51,"bs":1},{"t":95418,"p":5540,"v":61,"bs":2},{"t":95427,"p":5530,"v":131,"bs":1},{"t":95430,"p":5530,"v":10,"bs":1},{"t":95433,"p":5530,"v":36,"bs":1},{"t":95436,"p":5540,"v":61,"bs":2},{"t":95442,"p":5530,"v":91,"bs":1},{"t":95451,"p":5530,"v":9,"bs":2},{"t":95454,"p":5520,"v":364,"bs":1},{"t":95515,"p":5520,"v":176,"bs":2},{"t":95527,"p":5520,"v":155,"bs":1},{"t":95530,"p":5510,"v":341,"bs":1},{"t":95536,"p":5530,"v":50,"bs":2},{"t":95548,"p":5530,"v":2,"bs":2},{"t":95551,"p":5520,"v":1,"bs":1},{"t":95606,"p":5520,"v":60,"bs":1},{"t":95609,"p":5530,"v":60,"bs":2},{"t":95633,"p":5530,"v":20,"bs":2},{"t":95715,"p":5520,"v":13,"bs":1},{"t":95730,"p":5530,"v":106,"bs":2},{"t":95733,"p":5530,"v":8,"bs":1},{"t":95815,"p":5530,"v":40,"bs":1},{"t":95827,"p":5540,"v":7,"bs":2},{"t":95833,"p":5540,"v":283,"bs":2},{"t":95839,"p":5540,"v":20,"bs":1},{"t":95854,"p":5540,"v":20,"bs":1},{"t":95915,"p":5540,"v":4,"bs":1},{"t":95921,"p":5540,"v":12,"bs":1},{"t":95924,"p":5530,"v":245,"bs":1},{"t":95939,"p":5520,"v":349,"bs":1},{"t":95951,"p":5520,"v":162,"bs":1},{"t":95954,"p":5530,"v":4,"bs":2},{"t":95957,"p":5530,"v":10,"bs":1},{"t":100003,"p":5540,"v":20,"bs":2},{"t":100009,"p":5530,"v":50,"bs":1},{"t":100039,"p":5530,"v":183,"bs":1},{"t":100057,"p":5530,"v":8,"bs":2},{"t":100100,"p":5530,"v":30,"bs":2},{"t":100103,"p":5530,"v":14,"bs":1},{"t":100106,"p":5520,"v":268,"bs":1},{"t":100145,"p":5510,"v":341,"bs":1},{"t":100224,"p":5520,"v":60,"bs":1},{"t":100239,"p":5520,"v":10,"bs":1},{"t":100251,"p":5510,"v":1,"bs":1},{"t":100300,"p":5520,"v":40,"bs":1},{"t":100312,"p":5530,"v":7,"bs":2},{"t":100336,"p":5520,"v":63,"bs":1},{"t":100400,"p":5520,"v":4,"bs":1},{"t":100403,"p":5520,"v":28,"bs":1},{"t":100406,"p":5510,"v":341,"bs":1},{"t":100451,"p":5510,"v":207,"bs":1},{"t":100454,"p":5510,"v":1,"bs":1},{"t":100518,"p":5500,"v":233,"bs":1},{"t":100524,"p":5500,"v":573,"bs":2},{"t":100530,"p":5500,"v":5,"bs":1},{"t":100551,"p":5500,"v":1,"bs":1},{"t":100624,"p":5500,"v":3,"bs":1},{"t":100633,"p":5500,"v":113,"bs":1},{"t":100645,"p":5510,"v":135,"bs":2},{"t":100651,"p":5500,"v":35,"bs":1},{"t":100712,"p":5510,"v":17,"bs":2},{"t":100715,"p":5510,"v":30,"bs":2},{"t":100727,"p":5510,"v":100,"bs":1},{"t":100739,"p":5510,"v":20,"bs":1},{"t":100748,"p":5500,"v":312,"bs":1},{"t":100751,"p":5500,"v":34,"bs":1},{"t":100803,"p":5500,"v":1,"bs":1},{"t":100821,"p":5510,"v":10,"bs":2},{"t":100830,"p":5510,"v":20,"bs":1},{"t":100839,"p":5510,"v":5,"bs":2},{"t":100900,"p":5510,"v":1,"bs":2},{"t":100909,"p":5510,"v":7,"bs":2},{"t":100912,"p":5510,"v":27,"bs":2},{"t":100921,"p":5500,"v":321,"bs":1},{"t":100936,"p":5510,"v":5,"bs":1},{"t":100939,"p":5510,"v":68,"bs":1},{"t":100942,"p":5520,"v":100,"bs":2},{"t":100957,"p":5520,"v":10,"bs":2},{"t":101003,"p":5520,"v":65,"bs":2},{"t":101006,"p":5520,"v":10,"bs":2},{"t":101012,"p":5510,"v":1,"bs":1},{"t":101015,"p":5520,"v":89,"bs":2},{"t":101021,"p":5510,"v":226,"bs":1},{"t":101027,"p":5510,"v":140,"bs":2},{"t":101033,"p":5510,"v":16,"bs":1},{"t":101039,"p":5510,"v":78,"bs":1},{"t":101048,"p":5510,"v":66,"bs":1},{"t":101057,"p":5500,"v":1,"bs":1},{"t":101103,"p":5500,"v":202,"bs":1},{"t":101112,"p":5510,"v":19,"bs":2},{"t":101133,"p":5510,"v":50,"bs":1},{"t":101136,"p":5510,"v":60,"bs":1},{"t":101139,"p":5510,"v":121,"bs":1},{"t":101142,"p":5510,"v":10,"bs":2},{"t":101148,"p":5510,"v":133,"bs":2},{"t":101154,"p":5510,"v":100,"bs":1},{"t":101157,"p":5500,"v":249,"bs":1},{"t":101209,"p":5510,"v":21,"bs":1},{"t":101212,"p":5520,"v":1003,"bs":2},{"t":101233,"p":5510,"v":231,"bs":1},{"t":101248,"p":5510,"v":21,"bs":1},{"t":101254,"p":5510,"v":40,"bs":2},{"t":101257,"p":5530,"v":4,"bs":2},{"t":101324,"p":5520,"v":19,"bs":1},{"t":101333,"p":5520,"v":200,"bs":2},{"t":101336,"p":5520,"v":2,"bs":2},{"t":101339,"p":5520,"v":16,"bs":2},{"t":101345,"p":5520,"v":19,"bs":2},{"t":101351,"p":5530,"v":142,"bs":2},{"t":101409,"p":5530,"v":261,"bs":2},{"t":101415,"p":5530,"v":12,"bs":2},{"t":101421,"p":5530,"v":50,"bs":2},{"t":101424,"p":5520,"v":21,"bs":1},{"t":101430,"p":5520,"v":9,"bs":1},{"t":101433,"p":5520,"v":1,"bs":1},{"t":101442,"p":5510,"v":187,"bs":1},{"t":101457,"p":5530,"v":5,"bs":2},{"t":101503,"p":5520,"v":48,"bs":1},{"t":101506,"p":5520,"v":18,"bs":1},{"t":101515,"p":5520,"v":4,"bs":1},{"t":101542,"p":5530,"v":477,"bs":2},{"t":101548,"p":5520,"v":315,"bs":1},{"t":101551,"p":5520,"v":1,"bs":1},{"t":101557,"p":5530,"v":2,"bs":2},{"t":101603,"p":5520,"v":246,"bs":1},{"t":101606,"p":5520,"v":10,"bs":2},{"t":101612,"p":5520,"v":85,"bs":2},{"t":101621,"p":5520,"v":18,"bs":1},{"t":101624,"p":5520,"v":10,"bs":1},{"t":101630,"p":5530,"v":30,"bs":2},{"t":101645,"p":5520,"v":100,"bs":1},{"t":101715,"p":5510,"v":347,"bs":1},{"t":101809,"p":5520,"v":31,"bs":1},{"t":101830,"p":5520,"v":10,"bs":2},{"t":101833,"p":5510,"v":127,"bs":1},{"t":101842,"p":5510,"v":2,"bs":1},{"t":101848,"p":5520,"v":10,"bs":2},{"t":101851,"p":5520,"v":26,"bs":2},{"t":101903,"p":5520,"v":124,"bs":2},{"t":101918,"p":5520,"v":150,"bs":2},{"t":101933,"p":5520,"v":136,"bs":2},{"t":101942,"p":5510,"v":2,"bs":1},{"t":101945,"p":5510,"v":183,"bs":1},{"t":101951,"p":5510,"v":278,"bs":1},{"t":102000,"p":5510,"v":303,"bs":1},{"t":102003,"p":5520,"v":246,"bs":2},{"t":102039,"p":5530,"v":75,"bs":2},{"t":102042,"p":5530,"v":6,"bs":1},{"t":102057,"p":5520,"v":202,"bs":1},{"t":102115,"p":5520,"v":29,"bs":2},{"t":102118,"p":5520,"v":50,"bs":1},{"t":102121,"p":5510,"v":38,"bs":1},{"t":102154,"p":5520,"v":7,"bs":1},{"t":102209,"p":5510,"v":36,"bs":1},{"t":102215,"p":5520,"v":58,"bs":2},{"t":102251,"p":5520,"v":193,"bs":2},{"t":102348,"p":5520,"v":5,"bs":1},{"t":102403,"p":5550,"v":438,"bs":2},{"t":102418,"p":5520,"v":10,"bs":1},{"t":102445,"p":5520,"v":239,"bs":1},{"t":102448,"p":5540,"v":42,"bs":2},{"t":102457,"p":5540,"v":34,"bs":2},{"t":102533,"p":5530,"v":10,"bs":2},{"t":102554,"p":5540,"v":100,"bs":2},{"t":102612,"p":5520,"v":34,"bs":1},{"t":102630,"p":5540,"v":24,"bs":2},{"t":102648,"p":5550,"v":20,"bs":2},{"t":102651,"p":5520,"v":342,"bs":1},{"t":102700,"p":5520,"v":451,"bs":1},{"t":102703,"p":5520,"v":15,"bs":1},{"t":102709,"p":5520,"v":3,"bs":2},{"t":102712,"p":5510,"v":312,"bs":1},{"t":102715,"p":5520,"v":4,"bs":2},{"t":102751,"p":5510,"v":56,"bs":1},{"t":102803,"p":5500,"v":84,"bs":1},{"t":102812,"p":5500,"v":132,"bs":1},{"t":102821,"p":5500,"v":56,"bs":1},{"t":102827,"p":5500,"v":20,"bs":1},{"t":102830,"p":5500,"v":77,"bs":1},{"t":102833,"p":5500,"v":254,"bs":1},{"t":102839,"p":5500,"v":34,"bs":1},{"t":102854,"p":5510,"v":20,"bs":1},{"t":102900,"p":5500,"v":56,"bs":1},{"t":102909,"p":5500,"v":71,"bs":1},{"t":102915,"p":5500,"v":45,"bs":1},{"t":102924,"p":5500,"v":23,"bs":1},{"t":102933,"p":5500,"v":140,"bs":1},{"t":102942,"p":5500,"v":6,"bs":2},{"t":102945,"p":5490,"v":56,"bs":1},{"t":102954,"p":5490,"v":62,"bs":1},{"t":103003,"p":5490,"v":73,"bs":1},{"t":103021,"p":5490,"v":67,"bs":1},{"t":103030,"p":5500,"v":53,"bs":2},{"t":103033,"p":5500,"v":144,"bs":1},{"t":103042,"p":5500,"v":29,"bs":1},{"t":103054,"p":5500,"v":22,"bs":1},{"t":103103,"p":5500,"v":23,"bs":1},{"t":103203,"p":5500,"v":23,"bs":1},{"t":103215,"p":5510,"v":24,"bs":2},{"t":103224,"p":5510,"v":51,"bs":1},{"t":103230,"p":5510,"v":39,"bs":1},{"t":103239,"p":5510,"v":61,"bs":1},{"t":103251,"p":5500,"v":67,"bs":1},{"t":103309,"p":5500,"v":21,"bs":1},{"t":103321,"p":5490,"v":62,"bs":1},{"t":103327,"p":5490,"v":174,"bs":1},{"t":103348,"p":5480,"v":66,"bs":1},{"t":103400,"p":5480,"v":314,"bs":1},{"t":103415,"p":5470,"v":34,"bs":1},{"t":103418,"p":5500,"v":200,"bs":2},{"t":103424,"p":5470,"v":101,"bs":1},{"t":103436,"p":5470,"v":30,"bs":1},{"t":103442,"p":5460,"v":51,"bs":1},{"t":103503,"p":5480,"v":3,"bs":1},{"t":103521,"p":5470,"v":138,"bs":1},{"t":103536,"p":5480,"v":2,"bs":2},{"t":103542,"p":5480,"v":42,"bs":2},{"t":103557,"p":5500,"v":54,"bs":2},{"t":103633,"p":5490,"v":1,"bs":2},{"t":103648,"p":5490,"v":8,"bs":1},{"t":103709,"p":5480,"v":10,"bs":1},{"t":103748,"p":5480,"v":35,"bs":1},{"t":103754,"p":5480,"v":10,"bs":2},{"t":103757,"p":5480,"v":6,"bs":2},{"t":103803,"p":5480,"v":6,"bs":2},{"t":103806,"p":5480,"v":1,"bs":2},{"t":103809,"p":5480,"v":10,"bs":2},{"t":103827,"p":5480,"v":50,"bs":2},{"t":103830,"p":5480,"v":2,"bs":2},{"t":103839,"p":5480,"v":30,"bs":2},{"t":103851,"p":5470,"v":25,"bs":1},{"t":103906,"p":5490,"v":4,"bs":2},{"t":104018,"p":5480,"v":66,"bs":1},{"t":104118,"p":5480,"v":26,"bs":1},{"t":104121,"p":5480,"v":10,"bs":2},{"t":104127,"p":5480,"v":29,"bs":2},{"t":104145,"p":5470,"v":69,"bs":1},{"t":104200,"p":5480,"v":5,"bs":2},{"t":104212,"p":5480,"v":43,"bs":2},{"t":104224,"p":5480,"v":10,"bs":2},{"t":104227,"p":5480,"v":2,"bs":2},{"t":104248,"p":5480,"v":13,"bs":2},{"t":104254,"p":5480,"v":159,"bs":2},{"t":104321,"p":5480,"v":4,"bs":2},{"t":104327,"p":5480,"v":28,"bs":2},{"t":104336,"p":5480,"v":23,"bs":2},{"t":104345,"p":5480,"v":2,"bs":2},{"t":104348,"p":5480,"v":10,"bs":2},{"t":104403,"p":5480,"v":6,"bs":2},{"t":104412,"p":5480,"v":17,"bs":1},{"t":104418,"p":5480,"v":2,"bs":2},{"t":104527,"p":5480,"v":29,"bs":1},{"t":104536,"p":5480,"v":1,"bs":2},{"t":104600,"p":5470,"v":500,"bs":1},{"t":104621,"p":5480,"v":3,"bs":2},{"t":104800,"p":5480,"v":7,"bs":2},{"t":104806,"p":5480,"v":7,"bs":2},{"t":104815,"p":5480,"v":9,"bs":2},{"t":104821,"p":5470,"v":35,"bs":1},{"t":104903,"p":5470,"v":11,"bs":1},{"t":104912,"p":5480,"v":116,"bs":2},{"t":104945,"p":5490,"v":34,"bs":2},{"t":104954,"p":5480,"v":50,"bs":1},{"t":105021,"p":5480,"v":1,"bs":1},{"t":105048,"p":5480,"v":1,"bs":1},{"t":105109,"p":5480,"v":30,"bs":1},{"t":105118,"p":5490,"v":29,"bs":2},{"t":105136,"p":5490,"v":114,"bs":2},{"t":105151,"p":5490,"v":19,"bs":2},{"t":105154,"p":5500,"v":19,"bs":2},{"t":105209,"p":5500,"v":177,"bs":2},{"t":105315,"p":5500,"v":1,"bs":1},{"t":105357,"p":5500,"v":3,"bs":2},{"t":105412,"p":5500,"v":3,"bs":2},{"t":105509,"p":5490,"v":1,"bs":1},{"t":105600,"p":5500,"v":20,"bs":2},{"t":105633,"p":5490,"v":1,"bs":1},{"t":105645,"p":5500,"v":4,"bs":2},{"t":105651,"p":5500,"v":20,"bs":2},{"t":105718,"p":5500,"v":54,"bs":1},{"t":105724,"p":5500,"v":23,"bs":2},{"t":105748,"p":5490,"v":45,"bs":1},{"t":105848,"p":5490,"v":76,"bs":1},{"t":105927,"p":5490,"v":82,"bs":1},{"t":105930,"p":5490,"v":33,"bs":2},{"t":110006,"p":5480,"v":2,"bs":1},{"t":110018,"p":5480,"v":1,"bs":1},{"t":110054,"p":5500,"v":3,"bs":2},{"t":110124,"p":5480,"v":65,"bs":1},{"t":110209,"p":5480,"v":2,"bs":1},{"t":110221,"p":5480,"v":1,"bs":1},{"t":110248,"p":5500,"v":140,"bs":2},{"t":110318,"p":5500,"v":53,"bs":1},{"t":110421,"p":5500,"v":100,"bs":2},{"t":110424,"p":5500,"v":10,"bs":2},{"t":110448,"p":5500,"v":8,"bs":2},{"t":110515,"p":5500,"v":13,"bs":2},{"t":110530,"p":5480,"v":20,"bs":1},{"t":110545,"p":5480,"v":3,"bs":1},{"t":110615,"p":5480,"v":47,"bs":1},{"t":110724,"p":5490,"v":25,"bs":2},{"t":110727,"p":5480,"v":60,"bs":1},{"t":110806,"p":5480,"v":81,"bs":1},{"t":110824,"p":5490,"v":10,"bs":2},{"t":110951,"p":5490,"v":18,"bs":2},{"t":111000,"p":5480,"v":10,"bs":1},{"t":111009,"p":5480,"v":129,"bs":1},{"t":111018,"p":5480,"v":30,"bs":1},{"t":111027,"p":5480,"v":142,"bs":1},{"t":111051,"p":5470,"v":37,"bs":1},{"t":111054,"p":5470,"v":128,"bs":1},{"t":111118,"p":5470,"v":210,"bs":1},{"t":111124,"p":5470,"v":120,"bs":1},{"t":111203,"p":5470,"v":168,"bs":1},{"t":111218,"p":5460,"v":120,"bs":1},{"t":111242,"p":5460,"v":145,"bs":1},{"t":111300,"p":5460,"v":19,"bs":2},{"t":111303,"p":5460,"v":7,"bs":2},{"t":111312,"p":5460,"v":9,"bs":2},{"t":111336,"p":5460,"v":31,"bs":1},{"t":111351,"p":5460,"v":9,"bs":2},{"t":111409,"p":5460,"v":4,"bs":1},{"t":111436,"p":5450,"v":457,"bs":1},{"t":111445,"p":5450,"v":79,"bs":1},{"t":111500,"p":5440,"v":147,"bs":1},{"t":111503,"p":5450,"v":5,"bs":2},{"t":111506,"p":5440,"v":144,"bs":1},{"t":111515,"p":5440,"v":86,"bs":1},{"t":111518,"p":5440,"v":1,"bs":2},{"t":111524,"p":5460,"v":37,"bs":2},{"t":111530,"p":5460,"v":24,"bs":1},{"t":111557,"p":5440,"v":5,"bs":1},{"t":111603,"p":5460,"v":10,"bs":2},{"t":111618,"p":5440,"v":11,"bs":1},{"t":111624,"p":5440,"v":1,"bs":1},{"t":111651,"p":5450,"v":22,"bs":1},{"t":111657,"p":5450,"v":30,"bs":1},{"t":111706,"p":5450,"v":11,"bs":1},{"t":111724,"p":5440,"v":10,"bs":1},{"t":111730,"p":5450,"v":21,"bs":2},{"t":111736,"p":5440,"v":25,"bs":1},{"t":111751,"p":5440,"v":153,"bs":1},{"t":111757,"p":5450,"v":20,"bs":2},{"t":111830,"p":5440,"v":46,"bs":1},{"t":111848,"p":5440,"v":55,"bs":1},{"t":111857,"p":5440,"v":18,"bs":1},{"t":111906,"p":5440,"v":28,"bs":2},{"t":111915,"p":5450,"v":156,"bs":2},{"t":111927,"p":5450,"v":6,"bs":1},{"t":111942,"p":5450,"v":71,"bs":1},{"t":111957,"p":5450,"v":50,"bs":1},{"t":112009,"p":5460,"v":47,"bs":2},{"t":112024,"p":5460,"v":81,"bs":1},{"t":112027,"p":5470,"v":50,"bs":2},{"t":112045,"p":5460,"v":22,"bs":1},{"t":112115,"p":5450,"v":31,"bs":1},{"t":112127,"p":5450,"v":22,"bs":1},{"t":112145,"p":5450,"v":30,"bs":2},{"t":112154,"p":5440,"v":10,"bs":1},{"t":112212,"p":5450,"v":40,"bs":2},{"t":112224,"p":5450,"v":8,"bs":2},{"t":112227,"p":5440,"v":28,"bs":1},{"t":112254,"p":5440,"v":8,"bs":1},{"t":112333,"p":5450,"v":20,"bs":1},{"t":112418,"p":5450,"v":22,"bs":1},{"t":112457,"p":5450,"v":34,"bs":1},{"t":112500,"p":5450,"v":28,"bs":1},{"t":112554,"p":5450,"v":56,"bs":1},{"t":112645,"p":5460,"v":80,"bs":2},{"t":112654,"p":5460,"v":100,"bs":2},{"t":112703,"p":5460,"v":24,"bs":1},{"t":112730,"p":5450,"v":107,"bs":1},{"t":112754,"p":5460,"v":6,"bs":2},{"t":112809,"p":5460,"v":4,"bs":2},{"t":112848,"p":5470,"v":2,"bs":2},{"t":112857,"p":5470,"v":100,"bs":2},{"t":130000,"p":5470,"v":23,"bs":2},{"t":130003,"p":5460,"v":231,"bs":1},{"t":130006,"p":5450,"v":6,"bs":1},{"t":130009,"p":5480,"v":47,"bs":2},{"t":130015,"p":5460,"v":1,"bs":2},{"t":130039,"p":5450,"v":46,"bs":1},{"t":130230,"p":5470,"v":1,"bs":2},{"t":130315,"p":5460,"v":100,"bs":1},{"t":130539,"p":5470,"v":90,"bs":2},{"t":130548,"p":5460,"v":56,"bs":1},{"t":130557,"p":5460,"v":7,"bs":2},{"t":130612,"p":5450,"v":138,"bs":1},{"t":130700,"p":5450,"v":10,"bs":2},{"t":130921,"p":5450,"v":2,"bs":1},{"t":130927,"p":5470,"v":42,"bs":2},{"t":130954,"p":5470,"v":110,"bs":1},{"t":131030,"p":5470,"v":9,"bs":2},{"t":131036,"p":5470,"v":2,"bs":2},{"t":131112,"p":5470,"v":2,"bs":2},{"t":131121,"p":5470,"v":2,"bs":2},{"t":131130,"p":5470,"v":3,"bs":2},{"t":131139,"p":5470,"v":27,"bs":2},{"t":131215,"p":5460,"v":12,"bs":1},{"t":131218,"p":5460,"v":100,"bs":1},{"t":131236,"p":5470,"v":35,"bs":2},{"t":131254,"p":5470,"v":44,"bs":1},{"t":131330,"p":5480,"v":15,"bs":2},{"t":131342,"p":5480,"v":20,"bs":2},{"t":131400,"p":5480,"v":1,"bs":2},{"t":131409,"p":5480,"v":60,"bs":2},{"t":131412,"p":5470,"v":100,"bs":1},{"t":131430,"p":5480,"v":41,"bs":2},{"t":131442,"p":5480,"v":13,"bs":1},{"t":131451,"p":5470,"v":21,"bs":1},{"t":131503,"p":5470,"v":50,"bs":1},{"t":131533,"p":5470,"v":88,"bs":2},{"t":131630,"p":5460,"v":55,"bs":1},{"t":131706,"p":5460,"v":1,"bs":2},{"t":131718,"p":5460,"v":15,"bs":2},{"t":131724,"p":5460,"v":5,"bs":1},{"t":131739,"p":5460,"v":1,"bs":1},{"t":131751,"p":5460,"v":80,"bs":1},{"t":131806,"p":5460,"v":25,"bs":1},{"t":131827,"p":5470,"v":45,"bs":2},{"t":131857,"p":5470,"v":30,"bs":2},{"t":131906,"p":5470,"v":58,"bs":2},{"t":131927,"p":5460,"v":5,"bs":1},{"t":131936,"p":5460,"v":289,"bs":1},{"t":132018,"p":5460,"v":87,"bs":2},{"t":132045,"p":5460,"v":5,"bs":1},{"t":132109,"p":5460,"v":13,"bs":1},{"t":132121,"p":5460,"v":15,"bs":1},{"t":132209,"p":5450,"v":10,"bs":1},{"t":132224,"p":5450,"v":9,"bs":1},{"t":132242,"p":5460,"v":31,"bs":2},{"t":132254,"p":5450,"v":4,"bs":1},{"t":132312,"p":5450,"v":2,"bs":1},{"t":132409,"p":5460,"v":5,"bs":2},{"t":132500,"p":5470,"v":1,"bs":2},{"t":132512,"p":5470,"v":3,"bs":2},{"t":132515,"p":5440,"v":441,"bs":1},{"t":132533,"p":5440,"v":312,"bs":2},{"t":132718,"p":5470,"v":14,"bs":2},{"t":132745,"p":5450,"v":21,"bs":1},{"t":132848,"p":5440,"v":35,"bs":1},{"t":132921,"p":5450,"v":10,"bs":2},{"t":132951,"p":5460,"v":158,"bs":2},{"t":133012,"p":5470,"v":10,"bs":2},{"t":133024,"p":5470,"v":40,"bs":2},{"t":133039,"p":5470,"v":23,"bs":2},{"t":133057,"p":5460,"v":30,"bs":1},{"t":133142,"p":5460,"v":49,"bs":1},{"t":133212,"p":5460,"v":80,"bs":1},{"t":133227,"p":5460,"v":45,"bs":1},{"t":133251,"p":5460,"v":20,"bs":1},{"t":133336,"p":5460,"v":25,"bs":1},{"t":133430,"p":5460,"v":10,"bs":2},{"t":133524,"p":5450,"v":100,"bs":1},{"t":133542,"p":5450,"v":172,"bs":1},{"t":133557,"p":5440,"v":1,"bs":1},{"t":133600,"p":5450,"v":60,"bs":2},{"t":133630,"p":5450,"v":100,"bs":2},{"t":133651,"p":5450,"v":10,"bs":2},{"t":133654,"p":5450,"v":10,"bs":2},{"t":133700,"p":5450,"v":100,"bs":2},{"t":133703,"p":5450,"v":6,"bs":2},{"t":133709,"p":5450,"v":109,"bs":1},{"t":133712,"p":5450,"v":12,"bs":2},{"t":133718,"p":5450,"v":5,"bs":2},{"t":133727,"p":5450,"v":34,"bs":2},{"t":133745,"p":5450,"v":227,"bs":1},{"t":133751,"p":5450,"v":10,"bs":2},{"t":133754,"p":5450,"v":10,"bs":2},{"t":133800,"p":5450,"v":6,"bs":2},{"t":133806,"p":5450,"v":50,"bs":2},{"t":133812,"p":5450,"v":68,"bs":2},{"t":133815,"p":5450,"v":29,"bs":2},{"t":133839,"p":5460,"v":72,"bs":2},{"t":133909,"p":5460,"v":30,"bs":2},{"t":133930,"p":5460,"v":20,"bs":2},{"t":134115,"p":5470,"v":1,"bs":2},{"t":134203,"p":5460,"v":20,"bs":1},{"t":134218,"p":5470,"v":5,"bs":2},{"t":134227,"p":5460,"v":50,"bs":1},{"t":134345,"p":5460,"v":166,"bs":1},{"t":134503,"p":5450,"v":33,"bs":1},{"t":134506,"p":5460,"v":34,"bs":2},{"t":134509,"p":5450,"v":34,"bs":1},{"t":134530,"p":5450,"v":231,"bs":2},{"t":134545,"p":5450,"v":50,"bs":2},{"t":134548,"p":5450,"v":23,"bs":2},{"t":134606,"p":5450,"v":50,"bs":1},{"t":134609,"p":5450,"v":72,"bs":1},{"t":134612,"p":5450,"v":6,"bs":2},{"t":134618,"p":5460,"v":100,"bs":2},{"t":134621,"p":5440,"v":1,"bs":1},{"t":134645,"p":5450,"v":15,"bs":2},{"t":134709,"p":5450,"v":90,"bs":2},{"t":134848,"p":5450,"v":50,"bs":1},{"t":134900,"p":5460,"v":9,"bs":2},{"t":135133,"p":5460,"v":45,"bs":2},{"t":135142,"p":5460,"v":8,"bs":2},{"t":135145,"p":5450,"v":17,"bs":1},{"t":135148,"p":5460,"v":49,"bs":2},{"t":135151,"p":5460,"v":3,"bs":2},{"t":135157,"p":5460,"v":15,"bs":2},{"t":135209,"p":5460,"v":6,"bs":2},{"t":135254,"p":5450,"v":50,"bs":1},{"t":135457,"p":5460,"v":21,"bs":1},{"t":135503,"p":5450,"v":78,"bs":1},{"t":135642,"p":5460,"v":2,"bs":1},{"t":135715,"p":5460,"v":2,"bs":1},{"t":135721,"p":5470,"v":1,"bs":2},{"t":135733,"p":5470,"v":10,"bs":2},{"t":135815,"p":5470,"v":20,"bs":2},{"t":135833,"p":5470,"v":50,"bs":2},{"t":135857,"p":5470,"v":169,"bs":2},{"t":135930,"p":5470,"v":50,"bs":1},{"t":135939,"p":5470,"v":10,"bs":1},{"t":140033,"p":5470,"v":100,"bs":1},{"t":140124,"p":5470,"v":24,"bs":1},{"t":140215,"p":5470,"v":5,"bs":2},{"t":140239,"p":5470,"v":14,"bs":2},{"t":140251,"p":5470,"v":26,"bs":2},{"t":140254,"p":5470,"v":20,"bs":1},{"t":140354,"p":5470,"v":49,"bs":1},{"t":140357,"p":5480,"v":200,"bs":2},{"t":140409,"p":5480,"v":61,"bs":2},{"t":140418,"p":5480,"v":5,"bs":2},{"t":140527,"p":5480,"v":10,"bs":2},{"t":140542,"p":5480,"v":10,"bs":2},{"t":140545,"p":5480,"v":40,"bs":2},{"t":140557,"p":5480,"v":8,"bs":2},{"t":140621,"p":5490,"v":10,"bs":2},{"t":140645,"p":5490,"v":39,"bs":2},{"t":140715,"p":5480,"v":2,"bs":1},{"t":140754,"p":5490,"v":2,"bs":2},{"t":140821,"p":5480,"v":10,"bs":1},{"t":140827,"p":5490,"v":17,"bs":2},{"t":140830,"p":5480,"v":14,"bs":1},{"t":140921,"p":5490,"v":28,"bs":1},{"t":140939,"p":5490,"v":20,"bs":2},{"t":140945,"p":5490,"v":133,"bs":2},{"t":141015,"p":5500,"v":86,"bs":2},{"t":141018,"p":5490,"v":67,"bs":1},{"t":141027,"p":5490,"v":58,"bs":2},{"t":141109,"p":5490,"v":5,"bs":2},{"t":141130,"p":5480,"v":176,"bs":1},{"t":141139,"p":5490,"v":4,"bs":2},{"t":141200,"p":5480,"v":1,"bs":1},{"t":141230,"p":5480,"v":14,"bs":1},{"t":141233,"p":5490,"v":14,"bs":2},{"t":141312,"p":5480,"v":2,"bs":1},{"t":141421,"p":5470,"v":15,"bs":1},{"t":141527,"p":5480,"v":100,"bs":2},{"t":141530,"p":5480,"v":45,"bs":2},{"t":141533,"p":5480,"v":9,"bs":2},{"t":141654,"p":5480,"v":50,"bs":2},{"t":141706,"p":5480,"v":30,"bs":2},{"t":141712,"p":5480,"v":64,"bs":2},{"t":141727,"p":5490,"v":21,"bs":2},{"t":141812,"p":5500,"v":48,"bs":2},{"t":141833,"p":5500,"v":100,"bs":2},{"t":141836,"p":5510,"v":48,"bs":2},{"t":142033,"p":5500,"v":1,"bs":2},{"t":142109,"p":5500,"v":14,"bs":2},{"t":142127,"p":5490,"v":10,"bs":1},{"t":142148,"p":5490,"v":10,"bs":1},{"t":142200,"p":5490,"v":87,"bs":1},{"t":142227,"p":5490,"v":100,"bs":1},{"t":142257,"p":5490,"v":111,"bs":2},{"t":142306,"p":5490,"v":20,"bs":1},{"t":142400,"p":5490,"v":80,"bs":1},{"t":142403,"p":5490,"v":10,"bs":1},{"t":142421,"p":5490,"v":11,"bs":2},{"t":142506,"p":5490,"v":29,"bs":1},{"t":142533,"p":5480,"v":322,"bs":1},{"t":142715,"p":5480,"v":94,"bs":1},{"t":142733,"p":5480,"v":40,"bs":1},{"t":142745,"p":5480,"v":23,"bs":2},{"t":142818,"p":5480,"v":8,"bs":1},{"t":142821,"p":5480,"v":26,"bs":1},{"t":142854,"p":5470,"v":224,"bs":1},{"t":142906,"p":5480,"v":44,"bs":2},{"t":142954,"p":5470,"v":24,"bs":1},{"t":143009,"p":5470,"v":10,"bs":1},{"t":143012,"p":5480,"v":41,"bs":2},{"t":143027,"p":5480,"v":100,"bs":2},{"t":143033,"p":5470,"v":128,"bs":1},{"t":143036,"p":5480,"v":11,"bs":2},{"t":143042,"p":5490,"v":2,"bs":2},{"t":143048,"p":5490,"v":29,"bs":2},{"t":143106,"p":5500,"v":55,"bs":2},{"t":143121,"p":5510,"v":1,"bs":2},{"t":143130,"p":5500,"v":20,"bs":1},{"t":143148,"p":5510,"v":1,"bs":2},{"t":143203,"p":5500,"v":11,"bs":1},{"t":143230,"p":5500,"v":30,"bs":1},{"t":143300,"p":5510,"v":1,"bs":2},{"t":143321,"p":5500,"v":1,"bs":1},{"t":143400,"p":5500,"v":22,"bs":1},{"t":143415,"p":5500,"v":58,"bs":2},{"t":143457,"p":5490,"v":2,"bs":1},{"t":143506,"p":5490,"v":100,"bs":1},{"t":143524,"p":5490,"v":50,"bs":1},{"t":143533,"p":5490,"v":2,"bs":1},{"t":143624,"p":5490,"v":40,"bs":1},{"t":143627,"p":5490,"v":48,"bs":2},{"t":143636,"p":5490,"v":29,"bs":2},{"t":143657,"p":5490,"v":9,"bs":2},{"t":143721,"p":5490,"v":1,"bs":1},{"t":143736,"p":5490,"v":2,"bs":1},{"t":143748,"p":5500,"v":112,"bs":2},{"t":143809,"p":5500,"v":14,"bs":2},{"t":143815,"p":5500,"v":5,"bs":2},{"t":143818,"p":5500,"v":60,"bs":2},{"t":143836,"p":5500,"v":7,"bs":2},{"t":143851,"p":5490,"v":91,"bs":1},{"t":143857,"p":5500,"v":24,"bs":2},{"t":143909,"p":5500,"v":14,"bs":1},{"t":143939,"p":5510,"v":157,"bs":2},{"t":143942,"p":5510,"v":16,"bs":2},{"t":143945,"p":5510,"v":38,"bs":2},{"t":143948,"p":5510,"v":30,"bs":2},{"t":144009,"p":5510,"v":4,"bs":2},{"t":144024,"p":5520,"v":1,"bs":2},{"t":144036,"p":5520,"v":10,"bs":2},{"t":144130,"p":5510,"v":15,"bs":1},{"t":144206,"p":5510,"v":51,"bs":1},{"t":144209,"p":5510,"v":15,"bs":1},{"t":144218,"p":5510,"v":124,"bs":1},{"t":144242,"p":5510,"v":68,"bs":2},{"t":144300,"p":5510,"v":3,"bs":1},{"t":144324,"p":5510,"v":16,"bs":1},{"t":144330,"p":5520,"v":1,"bs":2},{"t":144339,"p":5520,"v":246,"bs":2},{"t":144348,"p":5530,"v":1,"bs":2},{"t":144357,"p":5530,"v":38,"bs":2},{"t":144421,"p":5530,"v":5,"bs":2},{"t":144439,"p":5520,"v":100,"bs":1},{"t":144442,"p":5520,"v":20,"bs":1},{"t":144451,"p":5520,"v":77,"bs":1},{"t":144457,"p":5520,"v":1,"bs":2},{"t":144500,"p":5520,"v":112,"bs":2},{"t":144512,"p":5510,"v":2,"bs":1},{"t":144515,"p":5520,"v":26,"bs":2},{"t":144536,"p":5520,"v":21,"bs":2},{"t":144557,"p":5510,"v":10,"bs":1},{"t":144603,"p":5520,"v":10,"bs":2},{"t":144606,"p":5520,"v":20,"bs":2},{"t":144609,"p":5510,"v":10,"bs":1},{"t":144615,"p":5520,"v":16,"bs":2},{"t":144630,"p":5510,"v":224,"bs":1},{"t":144642,"p":5510,"v":24,"bs":2},{"t":144654,"p":5520,"v":5,"bs":2},{"t":144721,"p":5510,"v":1,"bs":1},{"t":144730,"p":5510,"v":10,"bs":1},{"t":144739,"p":5520,"v":18,"bs":2},{"t":144745,"p":5510,"v":14,"bs":1},{"t":144748,"p":5510,"v":1,"bs":1},{"t":144757,"p":5510,"v":13,"bs":2},{"t":144812,"p":5510,"v":21,"bs":1},{"t":144818,"p":5510,"v":10,"bs":2},{"t":144833,"p":5500,"v":50,"bs":1},{"t":144857,"p":5500,"v":43,"bs":1},{"t":144900,"p":5510,"v":10,"bs":2},{"t":144912,"p":5510,"v":34,"bs":2},{"t":144918,"p":5510,"v":78,"bs":1},{"t":144921,"p":5500,"v":5,"bs":1},{"t":144930,"p":5520,"v":1,"bs":2},{"t":144939,"p":5510,"v":12,"bs":1},{"t":144957,"p":5500,"v":50,"bs":1},{"t":145000,"p":5510,"v":5,"bs":2},{"t":145003,"p":5500,"v":8,"bs":1},{"t":145024,"p":5500,"v":50,"bs":1},{"t":145057,"p":5500,"v":1,"bs":1},{"t":145106,"p":5510,"v":78,"bs":2},{"t":145112,"p":5500,"v":272,"bs":1},{"t":145115,"p":5500,"v":100,"bs":1},{"t":145124,"p":5510,"v":1,"bs":2},{"t":145139,"p":5510,"v":6,"bs":2},{"t":145142,"p":5520,"v":7,"bs":2},{"t":145209,"p":5520,"v":15,"bs":2},{"t":145239,"p":5510,"v":5,"bs":1},{"t":145248,"p":5520,"v":98,"bs":2},{"t":145251,"p":5510,"v":21,"bs":1},{"t":145300,"p":5510,"v":100,"bs":2},{"t":145306,"p":5510,"v":15,"bs":2},{"t":145312,"p":5520,"v":1,"bs":2},{"t":145315,"p":5510,"v":1,"bs":1},{"t":145351,"p":5500,"v":10,"bs":1},{"t":145415,"p":5510,"v":2,"bs":2},{"t":145418,"p":5510,"v":100,"bs":2},{"t":145421,"p":5510,"v":28,"bs":2},{"t":145430,"p":5510,"v":20,"bs":2},{"t":145457,"p":5500,"v":176,"bs":1},{"t":145518,"p":5500,"v":140,"bs":1},{"t":145524,"p":5490,"v":10,"bs":1},{"t":145539,"p":5490,"v":69,"bs":1},{"t":145542,"p":5500,"v":99,"bs":2},{"t":145557,"p":5490,"v":20,"bs":1},{"t":145600,"p":5500,"v":10,"bs":2},{"t":145603,"p":5500,"v":5,"bs":2},{"t":145606,"p":5490,"v":10,"bs":1},{"t":145612,"p":5490,"v":7,"bs":1},{"t":145615,"p":5500,"v":100,"bs":2},{"t":145621,"p":5500,"v":3,"bs":2},{"t":145627,"p":5500,"v":27,"bs":2},{"t":145630,"p":5500,"v":156,"bs":2},{"t":145633,"p":5500,"v":33,"bs":2},{"t":145639,"p":5490,"v":1,"bs":1},{"t":145645,"p":5500,"v":98,"bs":2},{"t":145654,"p":5500,"v":2,"bs":1},{"t":150059,"p":5500,"v":721,"bs":1}]