[{"t":91612,"p":11510,"v":9,"bs":4},{"t":91648,"p":11000,"v":14,"bs":4},{"t":91912,"p":11510,"v":9,"bs":4},{"t":92036,"p":11500,"v":10,"bs":4},{"t":92327,"p":11480,"v":10,"bs":4},{"t":92421,"p":11470,"v":10,"bs":4},{"t":92500,"p":11470,"v":21,"bs":2},{"t":93003,"p":11460,"v":14,"bs":1},{"t":93006,"p":11460,"v":1,"bs":2},{"t":93009,"p":11450,"v":14,"bs":2},{"t":93012,"p":11370,"v":4,"bs":1},{"t":93015,"p":11310,"v":20,"bs":1},{"t":93018,"p":11360,"v":5,"bs":2},{"t":93021,"p":11420,"v":7,"bs":2},{"t":93024,"p":11360,"v":1,"bs":1},{"t":93027,"p":11380,"v":2,"bs":2},{"t":93030,"p":11370,"v":3,"bs":1},{"t":93033,"p":11370,"v":21,"bs":1},{"t":93036,"p":11360,"v":5,"bs":1},{"t":93039,"p":11380,"v":12,"bs":2},{"t":93042,"p":11390,"v":1,"bs":2},{"t":93045,"p":11380,"v":3,"bs":1},{"t":93048,"p":11390,"v":1,"bs":2},{"t":93051,"p":11390,"v":3,"bs":2},{"t":93054,"p":11390,"v":6,"bs":2},{"t":93057,"p":11390,"v":2,"bs":2},{"t":93100,"p":11370,"v":4,"bs":1},{"t":93103,"p":11360,"v":5,"bs":1},{"t":93106,"p":11330,"v":11,"bs":1},{"t":93109,"p":11330,"v":1,"bs":1},{"t":93112,"p":11330,"v":1,"bs":1},{"t":93118,"p":11330,"v":2,"bs":1},{"t":93121,"p":11330,"v":5,"bs":2},{"t":93124,"p":11330,"v":3,"bs":2},{"t":93130,"p":11360,"v":3,"bs":2},{"t":93139,"p":11330,"v":2,"bs":1},{"t":93142,"p":11320,"v":3,"bs":1},{"t":93148,"p":11350,"v":5,"bs":2},{"t":93151,"p":11360,"v":10,"bs":2},{"t":93203,"p":11360,"v":7,"bs":2},{"t":93206,"p":11370,"v":12,"bs":2},{"t":93209,"p":11360,"v":2,"bs":1},{"t":93212,"p":11360,"v":8,"bs":1},{"t":93242,"p":11360,"v":1,"bs":2},{"t":93254,"p":11360,"v":1,"bs":2},{"t":93300,"p":11360,"v":6,"bs":2},{"t":93303,"p":11370,"v":6,"bs":2},{"t":93306,"p":11370,"v":2,"bs":2},{"t":93315,"p":11360,"v":1,"bs":1},{"t":93318,"p":11290,"v":74,"bs":1},{"t":93321,"p":11290,"v":3,"bs":1},{"t":93324,"p":11320,"v":3,"bs":1},{"t":93330,"p":11300,"v":1,"bs":1},{"t":93333,"p":11300,"v":1,"bs":1},{"t":93342,"p":11300,"v":11,"bs":1},{"t":93403,"p":11350,"v":9,"bs":1},{"t":93406,"p":11350,"v":1,"bs":2},{"t":93418,"p":11300,"v":21,"bs":1},{"t":93421,"p":11290,"v":9,"bs":1},{"t":93430,"p":11300,"v":9,"bs":2},{"t":93433,"p":11290,"v":32,"bs":1},{"t":93506,"p":11290,"v":1,"bs":1},{"t":93509,"p":11320,"v":2,"bs":2},{"t":93524,"p":11350,"v":3,"bs":2},{"t":93527,"p":11350,"v":4,"bs":2},{"t":93536,"p":11330,"v":20,"bs":1},{"t":93545,"p":11380,"v":3,"bs":2},{"t":93600,"p":11330,"v":43,"bs":1},{"t":93606,"p":11320,"v":2,"bs":1},{"t":93609,"p":11330,"v":5,"bs":1},{"t":93612,"p":11320,"v":5,"bs":1},{"t":93615,"p":11320,"v":2,"bs":1},{"t":93618,"p":11320,"v":1,"bs":1},{"t":93621,"p":11310,"v":2,"bs":1},{"t":93624,"p":11310,"v":1,"bs":1},{"t":93639,"p":11370,"v":12,"bs":2},{"t":93642,"p":11300,"v":61,"bs":1},{"t":93700,"p":11370,"v":31,"bs":2},{"t":93706,"p":11370,"v":1,"bs":2},{"t":93715,"p":11300,"v":6,"bs":1},{"t":93730,"p":11300,"v":10,"bs":1},{"t":93733,"p":11360,"v":1,"bs":2},{"t":93736,"p":11360,"v":1,"bs":2},{"t":93739,"p":11360,"v":1,"bs":2},{"t":93745,"p":11360,"v":2,"bs":2},{"t":93748,"p":11290,"v":14,"bs":1},{"t":93751,"p":11370,"v":112,"bs":2},{"t":93757,"p":11370,"v":11,"bs":1},{"t":93800,"p":11370,"v":3,"bs":1},{"t":93803,"p":11370,"v":2,"bs":1},{"t":93806,"p":11370,"v":2,"bs":1},{"t":93812,"p":11380,"v":1,"bs":2},{"t":93839,"p":11360,"v":30,"bs":2},{"t":93848,"p":11340,"v":1,"bs":2},{"t":93857,"p":11360,"v":26,"bs":2},{"t":93903,"p":11300,"v":156,"bs":1},{"t":93915,"p":11370,"v":54,"bs":2},{"t":93918,"p":11370,"v":2,"bs":2},{"t":93939,"p":11360,"v":7,"bs":2},{"t":94003,"p":11350,"v":1,"bs":2},{"t":94009,"p":11350,"v":23,"bs":2},{"t":94109,"p":11280,"v":22,"bs":1},{"t":94112,"p":11280,"v":2,"bs":2},{"t":94115,"p":11280,"v":2,"bs":2},{"t":94118,"p":11280,"v":8,"bs":2},{"t":94121,"p":11330,"v":2,"bs":2},{"t":94124,"p":11340,"v":7,"bs":2},{"t":94127,"p":11340,"v":4,"bs":2},{"t":94130,"p":11340,"v":9,"bs":2},{"t":94203,"p":11330,"v":1,"bs":2},{"t":94245,"p":11320,"v":2,"bs":1},{"t":94251,"p":11300,"v":1,"bs":1},{"t":94254,"p":11300,"v":19,"bs":2},{"t":94303,"p":11300,"v":1,"bs":1},{"t":94306,"p":11300,"v":17,"bs":1},{"t":94312,"p":11330,"v":3,"bs":2},{"t":94315,"p":11330,"v":9,"bs":2},{"t":94324,"p":11330,"v":1,"bs":2},{"t":94327,"p":11330,"v":3,"bs":2},{"t":94330,"p":11330,"v":2,"bs":2},{"t":94333,"p":11330,"v":1,"bs":2},{"t":94400,"p":11300,"v":5,"bs":1},{"t":94403,"p":11340,"v":22,"bs":2},{"t":94406,"p":11300,"v":20,"bs":1},{"t":94445,"p":11340,"v":5,"bs":2},{"t":94448,"p":11340,"v":31,"bs":1},{"t":94454,"p":11300,"v":1,"bs":1},{"t":94509,"p":11340,"v":1,"bs":2},{"t":94512,"p":11350,"v":12,"bs":2},{"t":94515,"p":11360,"v":7,"bs":2},{"t":94518,"p":11350,"v":6,"bs":2},{"t":94530,"p":11360,"v":6,"bs":2},{"t":94533,"p":11360,"v":3,"bs":2},{"t":94536,"p":11360,"v":3,"bs":2},{"t":94548,"p":11360,"v":1,"bs":2},{"t":94551,"p":11360,"v":2,"bs":2},{"t":94554,"p":11360,"v":9,"bs":2},{"t":94600,"p":11300,"v":101,"bs":1},{"t":94603,"p":11370,"v":1,"bs":2},{"t":94606,"p":11360,"v":2,"bs":1},{"t":94612,"p":11360,"v":1,"bs":2},{"t":94700,"p":11370,"v":3,"bs":2},{"t":94821,"p":11370,"v":2,"bs":2},{"t":94836,"p":11370,"v":1,"bs":2},{"t":94909,"p":11370,"v":1,"bs":2},{"t":94930,"p":11330,"v":1,"bs":1},{"t":94939,"p":11320,"v":12,"bs":1},{"t":94942,"p":11320,"v":19,"bs":2},{"t":94945,"p":11370,"v":19,"bs":2},{"t":95009,"p":11370,"v":1,"bs":2},{"t":95036,"p":11310,"v":7,"bs":1},{"t":95048,"p":11310,"v":10,"bs":1},{"t":95100,"p":11370,"v":1,"bs":2},{"t":95109,"p":11370,"v":5,"bs":2},{"t":95245,"p":11320,"v":1,"bs":1},{"t":95248,"p":11320,"v":2,"bs":1},{"t":95333,"p":11320,"v":16,"bs":1},{"t":95336,"p":11320,"v":33,"bs":2},{"t":95339,"p":11320,"v":1,"bs":2},{"t":95351,"p":11320,"v":1,"bs":2},{"t":95436,"p":11320,"v":5,"bs":2},{"t":95451,"p":11320,"v":1,"bs":2},{"t":95454,"p":11320,"v":1,"bs":2},{"t":95457,"p":11320,"v":6,"bs":2},{"t":95500,"p":11320,"v":3,"bs":2},{"t":95503,"p":11320,"v":2,"bs":2},{"t":95509,"p":11320,"v":8,"bs":2},{"t":95518,"p":11310,"v":23,"bs":1},{"t":95530,"p":11310,"v":6,"bs":1},{"t":95609,"p":11300,"v":6,"bs":1},{"t":95618,"p":11310,"v":5,"bs":2},{"t":95621,"p":11310,"v":1,"bs":1},{"t":95712,"p":11320,"v":4,"bs":2},{"t":95715,"p":11320,"v":23,"bs":2},{"t":95718,"p":11320,"v":17,"bs":2},{"t":95912,"p":11350,"v":1,"bs":2},{"t":95927,"p":11360,"v":24,"bs":2},{"t":95930,"p":11360,"v":1,"bs":1},{"t":95945,"p":11370,"v":20,"bs":2},{"t":100021,"p":11370,"v":19,"bs":2},{"t":100051,"p":11370,"v":1,"bs":1},{"t":100103,"p":11360,"v":10,"bs":1},{"t":100109,"p":11460,"v":83,"bs":2},{"t":100112,"p":11450,"v":3,"bs":1},{"t":100130,"p":11400,"v":1,"bs":2},{"t":100136,"p":11400,"v":2,"bs":2},{"t":100221,"p":11400,"v":1,"bs":2},{"t":100230,"p":11400,"v":1,"bs":2},{"t":100242,"p":11410,"v":2,"bs":2},{"t":100245,"p":11400,"v":1,"bs":1},{"t":100248,"p":11400,"v":1,"bs":2},{"t":100339,"p":11380,"v":5,"bs":2},{"t":100418,"p":11360,"v":4,"bs":1},{"t":100427,"p":11350,"v":60,"bs":1},{"t":100533,"p":11340,"v":4,"bs":2},{"t":100636,"p":11350,"v":5,"bs":2},{"t":100639,"p":11350,"v":28,"bs":2},{"t":100642,"p":11350,"v":1,"bs":2},{"t":100645,"p":11340,"v":1,"bs":2},{"t":100651,"p":11320,"v":10,"bs":1},{"t":100654,"p":11320,"v":3,"bs":2},{"t":100657,"p":11320,"v":1,"bs":2},{"t":100700,"p":11320,"v":1,"bs":2},{"t":100915,"p":11320,"v":10,"bs":1},{"t":100942,"p":11310,"v":10,"bs":1},{"t":100945,"p":11330,"v":2,"bs":2},{"t":101030,"p":11330,"v":1,"bs":2},{"t":101057,"p":11330,"v":20,"bs":2},{"t":101100,"p":11330,"v":5,"bs":2},{"t":101103,"p":11330,"v":6,"bs":2},{"t":101106,"p":11330,"v":3,"bs":2},{"t":101109,"p":11330,"v":1,"bs":2},{"t":101112,"p":11340,"v":1,"bs":2},{"t":101151,"p":11380,"v":1,"bs":2},{"t":101400,"p":11370,"v":4,"bs":2},{"t":101403,"p":11380,"v":1,"bs":2},{"t":101406,"p":11380,"v":2,"bs":2},{"t":101409,"p":11380,"v":1,"bs":2},{"t":101412,"p":11380,"v":1,"bs":1},{"t":101421,"p":11370,"v":1,"bs":1},{"t":101600,"p":11400,"v":5,"bs":2},{"t":101621,"p":11340,"v":1,"bs":1},{"t":101639,"p":11390,"v":7,"bs":2},{"t":101657,"p":11390,"v":5,"bs":2},{"t":101709,"p":11400,"v":49,"bs":2},{"t":101727,"p":11400,"v":41,"bs":1},{"t":101730,"p":11400,"v":9,"bs":1},{"t":101739,"p":11400,"v":4,"bs":1},{"t":101742,"p":11400,"v":22,"bs":1},{"t":101748,"p":11340,"v":1,"bs":1},{"t":101757,"p":11410,"v":3,"bs":2},{"t":101851,"p":11440,"v":46,"bs":2},{"t":101909,"p":11430,"v":1,"bs":1},{"t":101930,"p":11380,"v":8,"bs":1},{"t":102033,"p":11380,"v":3,"bs":2},{"t":102036,"p":11380,"v":1,"bs":2},{"t":102039,"p":11380,"v":1,"bs":2},{"t":102115,"p":11380,"v":3,"bs":2},{"t":102212,"p":11400,"v":6,"bs":2},{"t":102224,"p":11400,"v":4,"bs":2},{"t":102227,"p":11400,"v":28,"bs":2},{"t":102254,"p":11410,"v":39,"bs":2},{"t":102300,"p":11410,"v":60,"bs":2},{"t":102306,"p":11410,"v":2,"bs":2},{"t":102321,"p":11410,"v":5,"bs":1},{"t":102339,"p":11410,"v":3,"bs":1},{"t":102342,"p":11410,"v":2,"bs":2},{"t":102357,"p":11430,"v":100,"bs":2},{"t":102454,"p":11430,"v":1,"bs":2},{"t":102500,"p":11430,"v":3,"bs":2},{"t":102548,"p":11400,"v":7,"bs":1},{"t":102551,"p":11400,"v":24,"bs":2},{"t":102554,"p":11430,"v":5,"bs":2},{"t":102654,"p":11400,"v":1,"bs":1},{"t":102748,"p":11380,"v":30,"bs":1},{"t":102815,"p":11390,"v":1,"bs":1},{"t":102839,"p":11380,"v":240,"bs":1},{"t":102842,"p":11380,"v":18,"bs":1},{"t":102848,"p":11370,"v":2,"bs":1},{"t":102912,"p":11370,"v":1,"bs":1},{"t":102927,"p":11370,"v":2,"bs":1},{"t":102930,"p":11370,"v":1,"bs":1},{"t":103012,"p":11330,"v":22,"bs":1},{"t":103030,"p":11350,"v":3,"bs":2},{"t":103033,"p":11350,"v":4,"bs":2},{"t":103036,"p":11370,"v":84,"bs":2},{"t":103039,"p":11360,"v":1,"bs":1},{"t":103042,"p":11360,"v":1,"bs":1},{"t":103045,"p":11370,"v":1,"bs":2},{"t":103048,"p":11370,"v":1,"bs":2},{"t":103051,"p":11360,"v":2,"bs":1},{"t":103203,"p":11320,"v":3,"bs":1},{"t":103206,"p":11360,"v":1,"bs":2},{"t":103209,"p":11360,"v":1,"bs":2},{"t":103212,"p":11360,"v":1,"bs":2},{"t":103215,"p":11360,"v":1,"bs":2},{"t":103248,"p":11350,"v":2,"bs":2},{"t":103357,"p":11350,"v":2,"bs":2},{"t":103400,"p":11350,"v":4,"bs":1},{"t":103427,"p":11310,"v":10,"bs":1},{"t":103527,"p":11350,"v":2,"bs":2},{"t":103530,"p":11350,"v":9,"bs":1},{"t":103548,"p":11380,"v":102,"bs":2},{"t":103554,"p":11350,"v":6,"bs":1},{"t":103612,"p":11360,"v":1,"bs":1},{"t":103642,"p":11370,"v":1,"bs":1},{"t":103654,"p":11360,"v":2,"bs":1},{"t":103709,"p":11350,"v":60,"bs":1},{"t":103721,"p":11350,"v":1,"bs":1},{"t":103821,"p":11330,"v":18,"bs":1},{"t":103842,"p":11340,"v":2,"bs":2},{"t":103845,"p":11340,"v":1,"bs":2},{"t":103921,"p":11330,"v":1,"bs":1},{"t":103930,"p":11330,"v":2,"bs":1},{"t":103933,"p":11310,"v":18,"bs":1},{"t":103957,"p":11330,"v":4,"bs":2},{"t":104024,"p":11340,"v":9,"bs":2},{"t":104027,"p":11340,"v":10,"bs":2},{"t":104036,"p":11340,"v":2,"bs":2},{"t":104057,"p":11330,"v":1,"bs":1},{"t":104124,"p":11310,"v":27,"bs":1},{"t":104127,"p":11340,"v":1,"bs":2},{"t":104130,"p":11340,"v":8,"bs":2},{"t":104133,"p":11340,"v":1,"bs":2},{"t":104136,"p":11340,"v":1,"bs":2},{"t":104324,"p":11320,"v":30,"bs":1},{"t":104342,"p":11310,"v":30,"bs":1},{"t":104606,"p":11310,"v":1,"bs":1},{"t":104612,"p":11310,"v":17,"bs":1},{"t":104621,"p":11310,"v":5,"bs":2},{"t":104642,"p":11310,"v":1,"bs":2},{"t":104645,"p":11310,"v":30,"bs":2},{"t":104651,"p":11310,"v":1,"bs":2},{"t":104654,"p":11310,"v":6,"bs":2},{"t":104709,"p":11310,"v":3,"bs":2},{"t":104712,"p":11310,"v":38,"bs":2},{"t":104848,"p":11330,"v":2,"bs":2},{"t":104918,"p":11340,"v":10,"bs":2},{"t":104924,"p":11300,"v":3,"bs":1},{"t":104927,"p":11340,"v":4,"bs":2},{"t":104930,"p":11300,"v":1,"bs":1},{"t":105015,"p":11320,"v":1,"bs":2},{"t":105021,"p":11360,"v":1,"bs":1},{"t":105230,"p":11360,"v":1,"bs":2},{"t":105239,"p":11370,"v":1,"bs":2},{"t":105242,"p":11370,"v":3,"bs":1},{"t":105257,"p":11370,"v":4,"bs":2},{"t":105300,"p":11370,"v":8,"bs":1},{"t":105309,"p":11370,"v":2,"bs":2},{"t":105312,"p":11360,"v":1,"bs":1},{"t":105321,"p":11360,"v":1,"bs":2},{"t":105324,"p":11360,"v":5,"bs":1},{"t":105530,"p":11360,"v":1,"bs":1},{"t":105533,"p":11370,"v":1,"bs":2},{"t":105536,"p":11370,"v":8,"bs":2},{"t":105700,"p":11350,"v":1,"bs":2},{"t":105727,"p":11360,"v":6,"bs":2},{"t":105751,"p":11370,"v":5,"bs":2},{"t":105845,"p":11370,"v":1,"bs":2},{"t":105918,"p":11370,"v":1,"bs":2},{"t":110148,"p":11340,"v":1,"bs":2},{"t":110230,"p":11300,"v":14,"bs":1},{"t":110233,"p":11310,"v":2,"bs":2},{"t":110454,"p":11300,"v":38,"bs":1},{"t":110518,"p":11300,"v":20,"bs":1},{"t":110633,"p":11320,"v":2,"bs":2},{"t":110639,"p":11300,"v":6,"bs":1},{"t":110706,"p":11320,"v":3,"bs":2},{"t":110809,"p":11320,"v":2,"bs":2},{"t":110812,"p":11320,"v":3,"bs":2},{"t":110821,"p":11360,"v":8,"bs":2},{"t":110909,"p":11300,"v":49,"bs":1},{"t":110912,"p":11360,"v":2,"bs":2},{"t":110915,"p":11280,"v":6,"bs":1},{"t":111027,"p":11320,"v":2,"bs":2},{"t":111030,"p":11330,"v":1,"bs":2},{"t":111033,"p":11330,"v":2,"bs":2},{"t":111036,"p":11360,"v":5,"bs":2},{"t":111039,"p":11340,"v":2,"bs":2},{"t":111042,"p":11360,"v":2,"bs":2},{"t":111230,"p":11320,"v":6,"bs":1},{"t":111233,"p":11320,"v":12,"bs":1},{"t":111236,"p":11320,"v":8,"bs":1},{"t":111406,"p":11320,"v":4,"bs":1},{"t":111409,"p":11320,"v":2,"bs":1},{"t":111412,"p":11320,"v":1,"bs":1},{"t":111415,"p":11320,"v":2,"bs":1},{"t":111418,"p":11320,"v":1,"bs":1},{"t":111421,"p":11320,"v":2,"bs":1},{"t":111424,"p":11320,"v":3,"bs":1},{"t":111427,"p":11320,"v":1,"bs":1},{"t":111530,"p":11310,"v":1,"bs":1},{"t":111651,"p":11320,"v":2,"bs":2},{"t":111657,"p":11330,"v":1,"bs":2},{"t":111703,"p":11330,"v":1,"bs":1},{"t":111721,"p":11310,"v":1,"bs":1},{"t":111724,"p":11310,"v":1,"bs":2},{"t":111818,"p":11330,"v":3,"bs":2},{"t":111900,"p":11310,"v":2,"bs":1},{"t":111915,"p":11280,"v":10,"bs":1},{"t":112036,"p":11270,"v":40,"bs":1},{"t":112257,"p":11300,"v":1,"bs":2},{"t":112400,"p":11290,"v":1,"bs":1},{"t":112442,"p":11280,"v":1,"bs":2},{"t":112503,"p":11270,"v":2,"bs":1},{"t":112506,"p":11280,"v":1,"bs":2},{"t":112539,"p":11310,"v":1,"bs":2},{"t":112542,"p":11310,"v":1,"bs":2},{"t":112545,"p":11310,"v":1,"bs":2},{"t":112651,"p":11310,"v":7,"bs":2},{"t":112815,"p":11270,"v":27,"bs":1},{"t":112824,"p":11270,"v":2,"bs":1},{"t":112906,"p":11280,"v":1,"bs":2},{"t":130003,"p":11330,"v":1,"bs":2},{"t":130009,"p":11350,"v":23,"bs":2},{"t":130015,"p":11360,"v":38,"bs":2},{"t":130018,"p":11360,"v":6,"bs":2},{"t":130021,"p":11370,"v":2,"bs":2},{"t":130027,"p":11360,"v":3,"bs":1},{"t":130106,"p":11340,"v":1,"bs":1},{"t":130203,"p":11340,"v":1,"bs":1},{"t":130415,"p":11320,"v":1,"bs":2},{"t":130436,"p":11310,"v":53,"bs":1},{"t":130439,"p":11310,"v":11,"bs":2},{"t":130442,"p":11310,"v":1,"bs":1},{"t":130451,"p":11310,"v":8,"bs":1},{"t":130454,"p":11310,"v":5,"bs":2},{"t":130457,"p":11310,"v":6,"bs":2},{"t":130500,"p":11310,"v":1,"bs":2},{"t":130718,"p":11310,"v":5,"bs":1},{"t":130906,"p":11310,"v":26,"bs":2},{"t":130918,"p":11300,"v":2,"bs":2},{"t":131003,"p":11300,"v":8,"bs":2},{"t":131015,"p":11320,"v":1,"bs":2},{"t":131139,"p":11310,"v":1,"bs":1},{"t":131230,"p":11310,"v":14,"bs":2},{"t":131318,"p":11320,"v":1,"bs":2},{"t":131409,"p":11310,"v":1,"bs":1},{"t":131430,"p":11320,"v":2,"bs":2},{"t":131451,"p":11330,"v":5,"bs":2},{"t":131627,"p":11300,"v":34,"bs":1},{"t":131748,"p":11290,"v":2,"bs":1},{"t":131803,"p":11290,"v":5,"bs":1},{"t":132012,"p":11290,"v":20,"bs":1},{"t":132027,"p":11290,"v":1,"bs":1},{"t":132106,"p":11300,"v":2,"bs":2},{"t":132127,"p":11330,"v":1,"bs":2},{"t":132227,"p":11320,"v":6,"bs":2},{"t":132424,"p":11310,"v":1,"bs":2},{"t":132506,"p":11300,"v":1,"bs":2},{"t":132600,"p":11310,"v":20,"bs":2},{"t":132618,"p":11310,"v":4,"bs":2},{"t":132703,"p":11310,"v":20,"bs":2},{"t":132706,"p":11310,"v":18,"bs":2},{"t":132842,"p":11300,"v":1,"bs":1},{"t":132845,"p":11300,"v":4,"bs":2},{"t":132912,"p":11310,"v":1,"bs":2},{"t":132921,"p":11310,"v":1,"bs":2},{"t":132936,"p":11310,"v":1,"bs":2},{"t":132939,"p":11310,"v":2,"bs":2},{"t":132942,"p":11310,"v":1,"bs":2},{"t":133021,"p":11320,"v":60,"bs":2},{"t":133024,"p":11320,"v":1,"bs":2},{"t":133027,"p":11320,"v":1,"bs":2},{"t":133045,"p":11350,"v":7,"bs":2},{"t":133057,"p":11350,"v":2,"bs":2},{"t":133103,"p":11350,"v":28,"bs":1},{"t":133151,"p":11350,"v":5,"bs":1},{"t":133154,"p":11350,"v":12,"bs":1},{"t":133212,"p":11310,"v":2,"bs":1},{"t":133245,"p":11330,"v":1,"bs":2},{"t":133303,"p":11350,"v":5,"bs":2},{"t":133712,"p":11360,"v":52,"bs":2},{"t":133748,"p":11360,"v":8,"bs":1},{"t":133833,"p":11360,"v":10,"bs":2},{"t":133900,"p":11360,"v":1,"bs":2},{"t":133921,"p":11350,"v":17,"bs":1},{"t":134045,"p":11350,"v":5,"bs":1},{"t":134139,"p":11350,"v":2,"bs":2},{"t":134142,"p":11350,"v":6,"bs":2},{"t":134145,"p":11350,"v":5,"bs":2},{"t":134148,"p":11350,"v":1,"bs":2},{"t":134151,"p":11350,"v":2,"bs":2},{"t":134439,"p":11340,"v":5,"bs":2},{"t":134548,"p":11330,"v":3,"bs":1},{"t":134815,"p":11330,"v":1,"bs":2},{"t":134857,"p":11330,"v":9,"bs":2},{"t":135003,"p":11350,"v":1,"bs":2},{"t":135033,"p":11350,"v":3,"bs":1},{"t":135036,"p":11350,"v":1,"bs":1},{"t":135039,"p":11350,"v":1,"bs":2},{"t":135121,"p":11340,"v":1,"bs":1},{"t":135127,"p":11360,"v":3,"bs":2},{"t":135130,"p":11360,"v":1,"bs":2},{"t":135133,"p":11360,"v":1,"bs":2},{"t":135154,"p":11370,"v":17,"bs":2},{"t":135239,"p":11380,"v":12,"bs":2},{"t":135403,"p":11370,"v":1,"bs":1},{"t":135409,"p":11370,"v":1,"bs":1},{"t":135412,"p":11370,"v":1,"bs":1},{"t":135418,"p":11370,"v":1,"bs":1},{"t":135421,"p":11370,"v":7,"bs":1},{"t":135424,"p":11380,"v":7,"bs":2},{"t":135427,"p":11370,"v":5,"bs":1},{"t":135436,"p":11370,"v":1,"bs":1},{"t":135439,"p":11370,"v":1,"bs":1},{"t":135500,"p":11370,"v":1,"bs":1},{"t":135527,"p":11360,"v":2,"bs":2},{"t":135530,"p":11370,"v":2,"bs":2},{"t":135606,"p":11370,"v":3,"bs":2},{"t":135639,"p":11350,"v":6,"bs":1},{"t":135642,"p":11350,"v":1,"bs":1},{"t":135724,"p":11380,"v":1,"bs":2},{"t":135903,"p":11360,"v":1,"bs":2},{"t":135921,"p":11370,"v":20,"bs":2},{"t":135948,"p":11360,"v":4,"bs":1},{"t":140124,"p":11360,"v":2,"bs":2},{"t":140148,"p":11360,"v":2,"bs":2},{"t":140224,"p":11360,"v":26,"bs":2},{"t":140236,"p":11360,"v":18,"bs":2},{"t":140306,"p":11360,"v":5,"bs":2},{"t":140309,"p":11360,"v":9,"bs":2},{"t":140406,"p":11370,"v":4,"bs":2},{"t":140412,"p":11370,"v":3,"bs":2},{"t":140433,"p":11380,"v":28,"bs":2},{"t":140642,"p":11370,"v":7,"bs":1},{"t":140645,"p":11370,"v":3,"bs":2},{"t":140657,"p":11370,"v":1,"bs":2},{"t":140703,"p":11370,"v":4,"bs":2},{"t":140712,"p":11370,"v":1,"bs":2},{"t":140718,"p":11370,"v":13,"bs":2},{"t":140800,"p":11370,"v":25,"bs":1},{"t":140806,"p":11370,"v":2,"bs":1},{"t":140915,"p":11370,"v":9,"bs":1},{"t":140933,"p":11370,"v":1,"bs":2},{"t":140945,"p":11380,"v":15,"bs":2},{"t":140951,"p":11380,"v":30,"bs":2},{"t":140954,"p":11380,"v":1,"bs":2},{"t":141000,"p":11370,"v":6,"bs":1},{"t":141003,"p":11370,"v":6,"bs":2},{"t":141006,"p":11370,"v":8,"bs":2},{"t":141009,"p":11370,"v":22,"bs":2},{"t":141012,"p":11370,"v":10,"bs":2},{"t":141015,"p":11390,"v":23,"bs":2},{"t":141048,"p":11390,"v":30,"bs":2},{"t":141100,"p":11390,"v":2,"bs":2},{"t":141121,"p":11400,"v":16,"bs":2},{"t":141133,"p":11400,"v":2,"bs":2},{"t":141151,"p":11390,"v":40,"bs":1},{"t":141215,"p":11390,"v":17,"bs":1},{"t":141218,"p":11390,"v":3,"bs":2},{"t":141227,"p":11400,"v":24,"bs":2},{"t":141257,"p":11400,"v":10,"bs":2},{"t":141312,"p":11390,"v":30,"bs":1},{"t":141315,"p":11400,"v":10,"bs":2},{"t":141318,"p":11390,"v":80,"bs":1},{"t":141412,"p":11400,"v":22,"bs":2},{"t":141421,"p":11400,"v":27,"bs":2},{"t":141548,"p":11400,"v":1,"bs":1},{"t":141600,"p":11400,"v":7,"bs":2},{"t":141603,"p":11390,"v":24,"bs":1},{"t":141651,"p":11390,"v":10,"bs":1},{"t":141709,"p":11390,"v":3,"bs":1},{"t":141727,"p":11390,"v":3,"bs":2},{"t":141739,"p":11390,"v":4,"bs":2},{"t":141803,"p":11400,"v":22,"bs":2},{"t":141815,"p":11400,"v":18,"bs":2},{"t":141818,"p":11400,"v":1,"bs":2},{"t":141918,"p":11400,"v":10,"bs":1},{"t":141942,"p":11400,"v":5,"bs":2},{"t":142003,"p":11400,"v":3,"bs":1},{"t":142009,"p":11410,"v":18,"bs":2},{"t":142021,"p":11410,"v":1,"bs":2},{"t":142024,"p":11410,"v":1,"bs":2},{"t":142027,"p":11410,"v":1,"bs":1},{"t":142100,"p":11400,"v":15,"bs":1},{"t":142103,"p":11400,"v":7,"bs":1},{"t":142133,"p":11390,"v":30,"bs":1},{"t":142136,"p":11390,"v":9,"bs":1},{"t":142139,"p":11390,"v":2,"bs":1},{"t":142142,"p":11390,"v":15,"bs":1},{"t":142145,"p":11390,"v":5,"bs":1},{"t":142148,"p":11390,"v":8,"bs":1},{"t":142151,"p":11390,"v":1,"bs":1},{"t":142157,"p":11390,"v":5,"bs":1},{"t":142206,"p":11390,"v":2,"bs":1},{"t":142236,"p":11390,"v":1,"bs":1},{"t":142245,"p":11410,"v":102,"bs":2},{"t":142248,"p":11410,"v":21,"bs":1},{"t":142300,"p":11410,"v":30,"bs":1},{"t":142324,"p":11420,"v":7,"bs":2},{"t":142327,"p":11420,"v":27,"bs":2},{"t":142421,"p":11420,"v":22,"bs":2},{"t":142445,"p":11420,"v":5,"bs":2},{"t":142615,"p":11430,"v":23,"bs":2},{"t":142639,"p":11430,"v":7,"bs":2},{"t":142657,"p":11440,"v":26,"bs":2},{"t":142721,"p":11440,"v":3,"bs":2},{"t":142724,"p":11440,"v":12,"bs":1},{"t":142727,"p":11440,"v":15,"bs":1},{"t":142739,"p":11460,"v":173,"bs":2},{"t":142745,"p":11460,"v":1,"bs":1},{"t":142754,"p":11460,"v":22,"bs":2},{"t":142800,"p":11460,"v":15,"bs":1},{"t":142806,"p":11460,"v":1,"bs":1},{"t":142818,"p":11470,"v":44,"bs":2},{"t":142821,"p":11480,"v":1,"bs":2},{"t":142824,"p":11480,"v":19,"bs":2},{"t":142827,"p":11470,"v":10,"bs":1},{"t":142839,"p":11490,"v":20,"bs":2},{"t":142842,"p":11480,"v":5,"bs":1},{"t":142845,"p":11490,"v":4,"bs":2},{"t":142854,"p":11500,"v":3,"bs":2},{"t":142918,"p":11470,"v":14,"bs":1},{"t":142924,"p":11500,"v":30,"bs":2},{"t":142942,"p":11470,"v":10,"bs":1},{"t":142957,"p":11500,"v":20,"bs":2},{"t":143003,"p":11500,"v":2,"bs":2},{"t":143012,"p":11500,"v":7,"bs":2},{"t":143030,"p":11480,"v":6,"bs":1},{"t":143033,"p":11490,"v":15,"bs":2},{"t":143036,"p":11490,"v":15,"bs":1},{"t":143054,"p":11490,"v":3,"bs":1},{"t":143057,"p":11490,"v":11,"bs":1},{"t":143100,"p":11500,"v":45,"bs":2},{"t":143109,"p":11500,"v":46,"bs":2},{"t":143151,"p":11490,"v":9,"bs":2},{"t":143242,"p":11460,"v":2,"bs":1},{"t":143245,"p":11460,"v":26,"bs":2},{"t":143248,"p":11460,"v":5,"bs":2},{"t":143257,"p":11490,"v":61,"bs":2},{"t":143303,"p":11490,"v":1,"bs":2},{"t":143321,"p":11460,"v":14,"bs":1},{"t":143409,"p":11470,"v":1,"bs":1},{"t":143412,"p":11480,"v":11,"bs":2},{"t":143503,"p":11480,"v":20,"bs":2},{"t":143506,"p":11480,"v":1,"bs":2},{"t":143509,"p":11490,"v":2,"bs":2},{"t":143512,"p":11490,"v":7,"bs":2},{"t":143612,"p":11490,"v":6,"bs":1},{"t":143615,"p":11500,"v":40,"bs":2},{"t":143648,"p":11490,"v":8,"bs":1},{"t":143654,"p":11500,"v":1,"bs":2},{"t":143733,"p":11490,"v":4,"bs":1},{"t":143757,"p":11480,"v":6,"bs":1},{"t":143809,"p":11480,"v":15,"bs":2},{"t":143821,"p":11480,"v":2,"bs":2},{"t":144000,"p":11480,"v":2,"bs":2},{"t":144003,"p":11480,"v":6,"bs":2},{"t":144009,"p":11490,"v":28,"bs":2},{"t":144033,"p":11480,"v":3,"bs":1},{"t":144133,"p":11480,"v":1,"bs":1},{"t":144139,"p":11480,"v":5,"bs":1},{"t":144200,"p":11480,"v":1,"bs":1},{"t":144203,"p":11480,"v":5,"bs":1},{"t":144206,"p":11480,"v":3,"bs":1},{"t":144209,"p":11480,"v":5,"bs":1},{"t":144218,"p":11480,"v":8,"bs":2},{"t":144221,"p":11480,"v":2,"bs":2},{"t":144224,"p":11480,"v":2,"bs":2},{"t":144242,"p":11490,"v":4,"bs":2},{"t":144245,"p":11480,"v":4,"bs":1},{"t":144300,"p":11480,"v":1,"bs":1},{"t":144324,"p":11470,"v":40,"bs":1},{"t":144354,"p":11470,"v":14,"bs":1},{"t":144403,"p":11480,"v":4,"bs":2},{"t":144412,"p":11480,"v":10,"bs":2},{"t":144415,"p":11490,"v":1,"bs":2},{"t":144445,"p":11490,"v":1,"bs":2},{"t":144454,"p":11480,"v":1,"bs":1},{"t":144509,"p":11480,"v":6,"bs":1},{"t":144512,"p":11490,"v":3,"bs":2},{"t":144515,"p":11490,"v":8,"bs":2},{"t":144518,"p":11490,"v":3,"bs":2},{"t":144530,"p":11480,"v":4,"bs":1},{"t":144603,"p":11500,"v":1,"bs":2},{"t":144606,"p":11490,"v":12,"bs":1},{"t":144615,"p":11490,"v":7,"bs":2},{"t":144618,"p":11490,"v":2,"bs":1},{"t":144633,"p":11490,"v":61,"bs":2},{"t":144645,"p":11490,"v":10,"bs":1},{"t":144703,"p":11490,"v":10,"bs":1},{"t":144718,"p":11490,"v":1,"bs":1},{"t":144736,"p":11490,"v":20,"bs":1},{"t":144748,"p":11490,"v":11,"bs":1},{"t":144757,"p":11490,"v":1,"bs":2},{"t":144821,"p":11470,"v":5,"bs":1},{"t":144824,"p":11490,"v":3,"bs":2},{"t":144830,"p":11470,"v":45,"bs":1},{"t":144839,"p":11490,"v":2,"bs":2},{"t":144857,"p":11480,"v":2,"bs":2},{"t":144912,"p":11470,"v":5,"bs":1},{"t":144927,"p":11480,"v":2,"bs":2},{"t":144945,"p":11480,"v":10,"bs":2},{"t":145000,"p":11490,"v":6,"bs":2},{"t":145003,"p":11490,"v":3,"bs":2},{"t":145018,"p":11490,"v":46,"bs":2},{"t":145021,"p":11490,"v":4,"bs":2},{"t":145024,"p":11490,"v":13,"bs":2},{"t":145030,"p":11480,"v":2,"bs":1},{"t":145121,"p":11480,"v":20,"bs":1},{"t":145124,"p":11500,"v":2,"bs":2},{"t":145127,"p":11480,"v":5,"bs":1},{"t":145145,"p":11490,"v":12,"bs":2},{"t":145148,"p":11490,"v":1,"bs":2},{"t":145151,"p":11490,"v":1,"bs":2},{"t":145218,"p":11490,"v":6,"bs":2},{"t":145224,"p":11490,"v":7,"bs":1},{"t":145300,"p":11500,"v":5,"bs":2},{"t":145306,"p":11500,"v":35,"bs":2},{"t":145309,"p":11500,"v":30,"bs":2},{"t":145315,"p":11500,"v":23,"bs":2},{"t":145318,"p":11490,"v":10,"bs":1},{"t":145327,"p":11490,"v":5,"bs":2},{"t":145330,"p":11490,"v":4,"bs":2},{"t":145333,"p":11490,"v":3,"bs":2},{"t":145345,"p":11490,"v":3,"bs":2},{"t":145351,"p":11490,"v":4,"bs":2},{"t":145357,"p":11500,"v":3,"bs":2},{"t":145406,"p":11500,"v":4,"bs":2},{"t":145412,"p":11500,"v":1,"bs":2},{"t":145418,"p":11500,"v":11,"bs":2},{"t":145427,"p":11490,"v":9,"bs":1},{"t":145433,"p":11500,"v":4,"bs":2},{"t":145439,"p":11500,"v":3,"bs":2},{"t":145445,"p":11500,"v":21,"bs":2},{"t":145451,"p":11500,"v":75,"bs":2},{"t":145454,"p":11520,"v":9,"bs":2},{"t":145500,"p":11520,"v":4,"bs":2},{"t":145503,"p":11510,"v":3,"bs":2},{"t":145509,"p":11520,"v":4,"bs":2},{"t":145512,"p":11520,"v":2,"bs":2},{"t":145521,"p":11520,"v":9,"bs":2},{"t":145527,"p":11520,"v":4,"bs":2},{"t":145530,"p":11520,"v":5,"bs":2},{"t":145536,"p":11520,"v":3,"bs":2},{"t":145539,"p":11510,"v":15,"bs":1},{"t":145542,"p":11520,"v":11,"bs":2},{"t":145548,"p":11520,"v":3,"bs":2},{"t":145554,"p":11520,"v":2,"bs":2},{"t":145557,"p":11520,"v":11,"bs":2},{"t":145603,"p":11510,"v":14,"bs":1},{"t":145609,"p":11520,"v":18,"bs":2},{"t":145618,"p":11510,"v":4,"bs":1},{"t":145636,"p":11500,"v":8,"bs":1},{"t":145639,"p":11440,"v":213,"bs":1},{"t":150059,"p":11480,"v":183,"bs":2}]